det3d/__init__.py
det3d/utils.py
det3d/interface/__init__.py
det3d/interface/infer.py
det3d/models/__init__.py
det3d/models/centerpoint/__init__.py
det3d/models/centerpoint/boolmap.py
det3d/models/centerpoint/centerhead.py
det3d/models/centerpoint/ld_base_v1.py
det3d/models/centerpoint/model_nms_utils.py
det3d/models/centerpoint/resfpn.py
det3d/ops/__init__.py
det3d/ops/iou3d_nms/__init__.py
det3d/ops/iou3d_nms/iou3d_nms_utils.py
det3d/types/PointCloud.py
det3d/types/__init__.py
det3d-0.0.4.dist-info/LICENSE
det3d-0.0.4.dist-info/METADATA
det3d-0.0.4.dist-info/WHEEL
det3d-0.0.4.dist-info/top_level.txt
det3d-0.0.4.dist-info/RECORD
