Metadata-Version: 2.1
Name: det3d
Version: 0.0.4
Summary: A package of 3D object detection models
Home-page: https://github.com/leoxiang66/3D-Detection
Author: Tao Xiang
Author-email: xiang.tao@outlook.de
License: UNKNOWN
Platform: UNKNOWN
Classifier: Programming Language :: Python :: 3
Classifier: License :: OSI Approved :: MIT License
Requires-Dist: torch (==1.8.0)
Requires-Dist: numpy (==1.19.2)
